[
  {
    "code": "2383",
    "name": "台光電",
    "market": "TWSE",
    "foreignRank": 2,
    "trustRank": 12,
    "foreignAmt": 1969872327,
    "trustAmt": 674763546,
    "close": 6080.0,
    "cashDiv": false,
    "cashDivAmt": null,
    "divYear": null
  },
  {
    "code": "6182",
    "name": "合晶",
    "market": "TPEx",
    "foreignRank": 24,
    "trustRank": 8,
    "foreignAmt": 582820358,
    "trustAmt": 824126240,
    "close": 163.0,
    "cashDiv": true,
    "cashDivAmt": 2.5,
    "divYear": 2018
  },
  {
    "code": "2382",
    "name": "廣達",
    "market": "TWSE",
    "foreignRank": 29,
    "trustRank": 10,
    "foreignAmt": 460573078,
    "trustAmt": 739366589,
    "close": 377.0,
    "cashDiv": false,
    "cashDivAmt": null,
    "divYear": null
  },
  {
    "code": "6223",
    "name": "旺矽",
    "market": "TPEx",
    "foreignRank": 51,
    "trustRank": 27,
    "foreignAmt": 287914878,
    "trustAmt": 390479368,
    "close": 7380.0,
    "cashDiv": true,
    "cashDivAmt": 4.5,
    "divYear": 2020
  },
  {
    "code": "5483",
    "name": "中美晶",
    "market": "TPEx",
    "foreignRank": 8,
    "trustRank": 72,
    "foreignAmt": 1039588707,
    "trustAmt": 69128824,
    "close": 210.5,
    "cashDiv": true,
    "cashDivAmt": 5.5,
    "divYear": 2020
  },
  {
    "code": "6173",
    "name": "信昌電",
    "market": "TPEx",
    "foreignRank": 69,
    "trustRank": 62,
    "foreignAmt": 199033809,
    "trustAmt": 100589580,
    "close": 350.5,
    "cashDiv": true,
    "cashDivAmt": 4.3,
    "divYear": 2018
  }
]